IHC_PMS_Lib_Wrappers-0.4.0.data/data/examples/dhcp.xml
IHC_PMS_Lib_Wrappers-0.4.0.data/data/examples/methodSet-example.xml
ihcWrappers/__init__.py
ihcWrappers/commandDescription.py
ihcWrappers/device.py
ihcWrappers/deviceIdentification.py
ihcWrappers/eventDescription.py
ihcWrappers/finderResult.py
ihcWrappers/ftpItem.py
ihcWrappers/networkInterface.py
ihcWrappers/networkInterfaceTypes.py
ihcWrappers/odtc.py
ihcWrappers/odtcConfigXml.py
ihcWrappers/odtcDownloader.py
ihcWrappers/odtcFinder.py
ihcWrappers/odtcParamsXml.py
ihcWrappers/pms.py
ihcWrappers/responseData.py
ihcWrappers/responseDataGetAutoBoostCo2.py
ihcWrappers/responseDataGetCo2FlowStatus.py
ihcWrappers/responseDataGetConfiguration.py
ihcWrappers/responseDataGetDoorStatus.py
ihcWrappers/responseDataGetLastData.py
ihcWrappers/responseDataGetLiquidLevel.py
ihcWrappers/responseDataGetParametersOdtc.py
ihcWrappers/responseDataGetParametersScila.py
ihcWrappers/responseDataGetTemperature.py
ihcWrappers/responseDataGetValveStatus.py
ihcWrappers/responseDataReadActualTemperature.py
ihcWrappers/responseValue.py
ihcWrappers/responseValueGetAutoBoostCo2.py
ihcWrappers/responseValueGetCo2FlowStatus.py
ihcWrappers/responseValueGetConfiguration.py
ihcWrappers/responseValueGetDoorStatus.py
ihcWrappers/responseValueGetLastData.py
ihcWrappers/responseValueGetLiquidLevel.py
ihcWrappers/responseValueGetParametersOdtc.py
ihcWrappers/responseValueGetParametersScila.py
ihcWrappers/responseValueGetTemperature.py
ihcWrappers/responseValueGetValveStatus.py
ihcWrappers/responseValueReadActualTemperature.py
ihcWrappers/scila.py
ihcWrappers/scilaConfigXml.py
ihcWrappers/scilaDownloader.py
ihcWrappers/scilaFinder.py
ihcWrappers/scilaParamsXml.py
ihcWrappers/sensorValues.py
ihcWrappers/silaReturnValue.py
ihcWrappers/state.py
ihcWrappers/status.py
ihcWrappers/statusEventArgs.py
IHC_PMS_Lib_Wrappers-0.4.0.dist-info/LICENSE.txt
IHC_PMS_Lib_Wrappers-0.4.0.dist-info/METADATA
IHC_PMS_Lib_Wrappers-0.4.0.dist-info/WHEEL
IHC_PMS_Lib_Wrappers-0.4.0.dist-info/top_level.txt
IHC_PMS_Lib_Wrappers-0.4.0.dist-info/RECORD
