Metadata-Version: 2.1
Name: IHC-PMS-Lib-Wrappers
Version: 0.4.0
Summary: INHECO ODTC/SCILA .Net Library Wrappers
Author: Florian Ortner
Author-email: FOrtner@inheco.com
Project-URL: Bug Reports, https://github.com/F9R/ihcpmslib-wrappers/issues
Project-URL: Source, https://github.com/F9R/ihcpmslib-wrappers
Keywords: inheco,odtc,scila,wrapper,pythonnet
Classifier: Development Status :: 4 - Beta
Classifier: Intended Audience :: Developers
Classifier: Topic :: Software Development :: Libraries :: Application Frameworks
Classifier: Topic :: Scientific/Engineering :: Bio-Informatics
Classifier: License :: OSI Approved :: BSD License
Classifier: Programming Language :: Python :: 3
Classifier: Programming Language :: Python :: 3.8
Classifier: Programming Language :: Python :: 3.9
Classifier: Programming Language :: Python :: 3.10
Classifier: Programming Language :: Python :: 3 :: Only
Requires-Python: >=3.6, <4
License-File: LICENSE.txt
Requires-Dist: pythonnet (>=2.5.2)
